<?xml version="1.0" encoding="UTF-8"?>
<PAGE width="419.64" height="595.32" number="234" id="p234"><MEDIABOX x1="0" y1="0" x2="419.64" y2="595.32"/><CROPBOX x1="0" y1="0" x2="419.64" y2="595.32"/><BLEEDBOX x1="0" y1="0" x2="419.64" y2="595.32"/><ARTBOX x1="0" y1="0" x2="419.64" y2="595.32"/><TRIMBOX x1="0" y1="0" x2="419.64" y2="595.32"/><TEXT width="12.78" height="7.668" id="p234_t1" x="203.45" y="569.101"><TOKEN sid="p234_s22946" id="p234_w1" font-name="Times New Roman" symbolic="yes" serif="yes" fixed-width="yes" bold="no" italic="no" font-size="8.52" font-color="#000000" rotation="0" angle="0" x="203.45" y="569.101" base="574.92" width="12.78" height="7.668">234</TOKEN></TEXT><TEXT width="131.166" height="9" id="p234_t2" x="56.424" y="46.08"><TOKEN sid="p234_s22949" id="p234_w2" font-name="IPA¾©" bold="no" italic="no" font-size="9" font-color="#000000" rotation="0" angle="0" x="56.424" y="46.08" base="54" width="131.166" height="9">思わず私はぷっと笑ってしまった。</TOKEN></TEXT><TEXT width="147.486" height="9" id="p234_t3" x="56.424" y="63.02"><TOKEN sid="p234_s22952" id="p234_w3" font-name="ipa¾©" bold="no" italic="no" font-size="9" font-color="#000000" rotation="0" angle="0" x="56.424" y="63.02" base="70.94" width="147.486" height="9">間髪いれず、じろっと見てくるレ゗ン。</TOKEN></TEXT><TEXT width="49.8" height="9" id="p234_t4" x="56.424" y="80.06"><TOKEN sid="p234_s22955" id="p234_w4" font-name="ipa¾©" bold="no" italic="no" font-size="9" font-color="#000000" rotation="0" angle="0" x="56.424" y="80.06" base="87.98" width="49.8" height="9">……ごめん。</TOKEN></TEXT><TEXT width="162.434" height="10.125" id="p234_t5" x="48.264" y="97.052"><TOKEN sid="p234_s22957" id="p234_w5" href="http://mindsc.ape.jp/klel/yui.cgi?xik=enxik&amp;axn=axnyui&amp;ism=ismyui&amp;rein=an&amp;ziko=ilm" font-name="kardinal" bold="no" italic="no" font-size="9" font-color="#000000" rotation="0" angle="0" x="48.264" y="97.052" base="104.54" width="10.317" height="10.125">"an</TOKEN><TOKEN sid="p234_s22958" id="p234_w6" href="http://mindsc.ape.jp/klel/yui.cgi?xik=enxik&amp;axn=axnyui&amp;ism=ismyui&amp;rein=en&amp;ziko=ilm" font-name="kardinal" bold="no" italic="no" font-size="9" font-color="#000000" rotation="0" angle="0" x="62.184" y="97.052" base="104.54" width="9.957" height="10.125">en</TOKEN><TOKEN sid="p234_s22959" id="p234_w7" href="http://mindsc.ape.jp/klel/yui.cgi?xik=enxik&amp;axn=axnyui&amp;ism=ismyui&amp;rein=nalx&amp;ziko=ilm" font-name="kardinal" bold="no" italic="no" font-size="9" font-color="#000000" rotation="0" angle="0" x="75.744" y="97.052" base="104.54" width="11.205" height="10.125">nalx</TOKEN><TOKEN sid="p234_s22960" id="p234_w8" href="http://mindsc.ape.jp/klel/yui.cgi?xik=enxik&amp;axn=axnyui&amp;ism=ismyui&amp;rein=xion&amp;ziko=ilm" font-name="kardinal" bold="no" italic="no" font-size="9" font-color="#000000" rotation="0" angle="0" x="90.624" y="97.052" base="104.54" width="16.92" height="10.125">xion</TOKEN><TOKEN sid="p234_s22961" id="p234_w9" href="http://mindsc.ape.jp/klel/yui.cgi?xik=enxik&amp;axn=axnyui&amp;ism=ismyui&amp;rein=tet&amp;ziko=ilm" font-name="kardinal" bold="no" italic="no" font-size="9" font-color="#000000" rotation="0" angle="0" x="111.14" y="97.052" base="104.54" width="9.09" height="10.125">tet</TOKEN><TOKEN sid="p234_s22962" id="p234_w10" href="http://mindsc.ape.jp/klel/yui.cgi?xik=enxik&amp;axn=axnyui&amp;ism=ismyui&amp;rein=ti&amp;ziko=ilm" font-name="kardinal" bold="no" italic="no" font-size="9" font-color="#000000" rotation="0" angle="0" x="123.86" y="97.052" base="104.54" width="7.008" height="10.125">ti</TOKEN><TOKEN sid="p234_s22963" id="p234_w11" href="http://mindsc.ape.jp/klel/yui.cgi?xik=enxik&amp;axn=axnyui&amp;ism=ismyui&amp;rein=man&amp;ziko=ilm" font-name="kardinal" bold="no" italic="no" font-size="9" font-color="#000000" rotation="0" angle="0" x="134.42" y="97.052" base="104.54" width="11.52" height="10.125">man</TOKEN><TOKEN sid="p234_s22964" id="p234_w12" href="http://mindsc.ape.jp/klel/yui.cgi?xik=enxik&amp;axn=axnyui&amp;ism=ismyui&amp;rein=ti&amp;ziko=ilm" font-name="kardinal" bold="no" italic="no" font-size="9" font-color="#000000" rotation="0" angle="0" x="149.57" y="97.052" base="104.54" width="7.008" height="10.125">ti</TOKEN><TOKEN sid="p234_s22965" id="p234_w13" href="http://mindsc.ape.jp/klel/yui.cgi?xik=enxik&amp;axn=axnyui&amp;ism=ismyui&amp;rein=et&amp;ziko=ilm" font-name="kardinal" bold="no" italic="no" font-size="9" font-color="#000000" rotation="0" angle="0" x="160.13" y="97.052" base="104.54" width="7.056" height="10.125">et</TOKEN><TOKEN sid="p234_s22966" id="p234_w14" href="http://mindsc.ape.jp/klel/yui.cgi?xik=enxik&amp;axn=axnyui&amp;ism=ismyui&amp;rein=fim&amp;ziko=ilm" font-name="kardinal" bold="no" italic="no" font-size="9" font-color="#000000" rotation="0" angle="0" x="170.81" y="97.052" base="104.54" width="16.203" height="10.125">fim,</TOKEN><TOKEN sid="p234_s22967" id="p234_w15" href="http://mindsc.ape.jp/klel/yui.cgi?xik=enxik&amp;axn=axnyui&amp;ism=ismyui&amp;rein=yunk&amp;ziko=ilm" font-name="kardinal" bold="no" italic="no" font-size="9" font-color="#000000" rotation="0" angle="0" x="190.61" y="97.052" base="104.54" width="20.088" height="10.125">yunk"</TOKEN></TEXT><TEXT width="196.446" height="9" id="p234_t6" x="56.424" y="114.02"><TOKEN sid="p234_s22970" id="p234_w16" font-name="ipa¾©" bold="no" italic="no" font-size="9" font-color="#000000" rotation="0" angle="0" x="56.424" y="114.02" base="121.94" width="196.446" height="9">レ゗ンはうっと唸って黙った。言い返せないようだ。</TOKEN></TEXT><TEXT width="316.092" height="9" id="p234_t7" x="56.424" y="131.06"><TOKEN sid="p234_s22973" id="p234_w17" font-name="ipa¾©" bold="no" italic="no" font-size="9" font-color="#000000" rotation="0" angle="0" x="56.424" y="131.06" base="138.98" width="316.092" height="9">ゕルオ゚さんは慣れた手つきで自転車のゞァを壊した。デーゲ上はまだ今の女の子たち</TOKEN></TEXT><TEXT width="324.252" height="9" id="p234_t8" x="48.264" y="148.1"><TOKEN sid="p234_s22974" id="p234_w18" font-name="ipa¾©" bold="no" italic="no" font-size="9" font-color="#000000" rotation="0" angle="0" x="48.264" y="148.1" base="156.02" width="324.252" height="9">が自転車を使っていることになっている。私たちが盗んでも彼女たちが借りたというとこ</TOKEN></TEXT><TEXT width="114.963" height="9" id="p234_t9" x="48.264" y="165.05"><TOKEN sid="p234_s22975" id="p234_w19" font-name="ipa¾©" bold="no" italic="no" font-size="9" font-color="#000000" rotation="0" angle="0" x="48.264" y="165.05" base="172.97" width="114.963" height="9">ろまでしか国は把握できない。</TOKEN></TEXT><TEXT width="315.961" height="10.125" id="p234_t10" x="48.264" y="182.042"><TOKEN sid="p234_s22977" id="p234_w20" href="http://mindsc.ape.jp/klel/yui.cgi?xik=enxik&amp;axn=axnyui&amp;ism=ismyui&amp;rein=lala&amp;ziko=ilm" font-name="kardinal" bold="no" italic="no" font-size="9" font-color="#000000" rotation="0" angle="0" x="48.264" y="182.042" base="189.53" width="10.464" height="10.125">"lala</TOKEN><TOKEN sid="p234_s22978" id="p234_w21" href="http://mindsc.ape.jp/klel/yui.cgi?xik=enxik&amp;axn=axnyui&amp;ism=ismyui&amp;rein=es&amp;ziko=ilm" font-name="kardinal" bold="no" italic="no" font-size="9" font-color="#000000" rotation="0" angle="0" x="62.304" y="182.042" base="189.53" width="7.176" height="10.125">es</TOKEN><TOKEN sid="p234_s22979" id="p234_w22" href="http://mindsc.ape.jp/klel/yui.cgi?xik=enxik&amp;axn=axnyui&amp;ism=ismyui&amp;rein=tyu&amp;ziko=ilm" font-name="kardinal" bold="no" italic="no" font-size="9" font-color="#000000" rotation="0" angle="0" x="73.104" y="182.042" base="189.53" width="11.871" height="10.125">tyu</TOKEN><TOKEN sid="p234_s22980" id="p234_w23" href="http://mindsc.ape.jp/klel/yui.cgi?xik=enxik&amp;axn=axnyui&amp;ism=ismyui&amp;rein=ser&amp;ziko=ilm" font-name="kardinal" bold="no" italic="no" font-size="9" font-color="#000000" rotation="0" angle="0" x="88.584" y="182.042" base="189.53" width="11.871" height="10.125">ser</TOKEN><TOKEN sid="p234_s22981" id="p234_w24" href="http://mindsc.ape.jp/klel/yui.cgi?xik=enxik&amp;axn=axnyui&amp;ism=ismyui&amp;rein=rigom&amp;ziko=ilm" font-name="kardinal" bold="no" italic="no" font-size="9" font-color="#000000" rotation="0" angle="0" x="104.06" y="182.042" base="189.53" width="23.751" height="10.125">rigom</TOKEN><TOKEN sid="p234_s22982" id="p234_w25" href="http://mindsc.ape.jp/klel/yui.cgi?xik=enxik&amp;axn=axnyui&amp;ism=ismyui&amp;rein=e&amp;ziko=ilm" font-name="kardinal" bold="no" italic="no" font-size="9" font-color="#000000" rotation="0" angle="0" x="131.42" y="182.042" base="189.53" width="5.157" height="10.125">e</TOKEN><TOKEN sid="p234_s22983" id="p234_w26" href="http://mindsc.ape.jp/klel/yui.cgi?xik=enxik&amp;axn=axnyui&amp;ism=ismyui&amp;rein=yame&amp;ziko=ilm" font-name="kardinal" bold="no" italic="no" font-size="9" font-color="#000000" rotation="0" angle="0" x="140.21" y="182.042" base="189.53" width="21.123" height="10.125">yame...</TOKEN><TOKEN sid="p234_s22984" id="p234_w27" href="http://mindsc.ape.jp/klel/yui.cgi?xik=enxik&amp;axn=axnyui&amp;ism=ismyui&amp;rein=leim&amp;ziko=ilm" font-name="kardinal" bold="no" italic="no" font-size="9" font-color="#000000" rotation="0" angle="0" x="165.05" y="182.042" base="189.53" width="17.643" height="10.125">leim,</TOKEN><TOKEN sid="p234_s22985" id="p234_w28" href="http://mindsc.ape.jp/klel/yui.cgi?xik=enxik&amp;axn=axnyui&amp;ism=ismyui&amp;rein=yame&amp;ziko=ilm" font-name="kardinal" bold="no" italic="no" font-size="9" font-color="#000000" rotation="0" angle="0" x="186.29" y="182.042" base="189.53" width="16.308" height="10.125">yame</TOKEN><TOKEN sid="p234_s22986" id="p234_w29" href="http://mindsc.ape.jp/klel/yui.cgi?xik=enxik&amp;axn=axnyui&amp;ism=ismyui&amp;rein=em&amp;ziko=ilm" font-name="kardinal" bold="no" italic="no" font-size="9" font-color="#000000" rotation="0" angle="0" x="206.21" y="182.042" base="189.53" width="9.957" height="10.125">em</TOKEN><TOKEN sid="p234_s22987" id="p234_w30" href="http://mindsc.ape.jp/klel/yui.cgi?xik=enxik&amp;axn=axnyui&amp;ism=ismyui&amp;rein=rig&amp;ziko=ilm" font-name="kardinal" bold="no" italic="no" font-size="9" font-color="#000000" rotation="0" angle="0" x="219.77" y="182.042" base="189.53" width="14.391" height="10.125">rig</TOKEN><TOKEN sid="p234_s22988" id="p234_w31" href="http://mindsc.ape.jp/klel/yui.cgi?xik=enxik&amp;axn=axnyui&amp;ism=ismyui&amp;rein=ol&amp;ziko=ilm" font-name="kardinal" bold="no" italic="no" font-size="9" font-color="#000000" rotation="0" angle="0" x="237.91" y="182.042" base="189.53" width="6.621" height="10.125">ol</TOKEN><TOKEN sid="p234_s22989" id="p234_w32" href="http://mindsc.ape.jp/klel/yui.cgi?xik=enxik&amp;axn=axnyui&amp;ism=ismyui&amp;rein=el&amp;ziko=ilm" font-name="kardinal" bold="no" italic="no" font-size="9" font-color="#000000" rotation="0" angle="0" x="248.11" y="182.042" base="189.53" width="6.861" height="10.125">el</TOKEN><TOKEN sid="p234_s22990" id="p234_w33" href="http://mindsc.ape.jp/klel/yui.cgi?xik=enxik&amp;axn=axnyui&amp;ism=ismyui&amp;rein=rig&amp;ziko=ilm" font-name="kardinal" bold="no" italic="no" font-size="9" font-color="#000000" rotation="0" angle="0" x="258.55" y="182.042" base="189.53" width="14.391" height="10.125">rig</TOKEN><TOKEN sid="p234_s22991" id="p234_w34" href="http://mindsc.ape.jp/klel/yui.cgi?xik=enxik&amp;axn=axnyui&amp;ism=ismyui&amp;rein=kuki&amp;ziko=ilm" font-name="kardinal" bold="no" italic="no" font-size="9" font-color="#000000" rotation="0" angle="0" x="276.55" y="182.042" base="189.53" width="15.243" height="10.125">kuki.</TOKEN><TOKEN sid="p234_s22992" id="p234_w35" href="http://mindsc.ape.jp/klel/yui.cgi?xik=enxik&amp;axn=axnyui&amp;ism=ismyui&amp;rein=tal&amp;ziko=ilm" font-name="kardinal" bold="no" italic="no" font-size="9" font-color="#000000" rotation="0" angle="0" x="295.39" y="182.042" base="189.53" width="10.563" height="10.125">tal...</TOKEN><TOKEN sid="p234_s22993" id="p234_w36" href="http://mindsc.ape.jp/klel/yui.cgi?xik=enxik&amp;axn=axnyui&amp;ism=ismyui&amp;rein=es&amp;ziko=ilm" font-name="kardinal" bold="no" italic="no" font-size="9" font-color="#000000" rotation="0" angle="0" x="309.55" y="182.042" base="189.53" width="7.056" height="10.125">es</TOKEN><TOKEN sid="p234_s22994" id="p234_w37" href="http://mindsc.ape.jp/klel/yui.cgi?xik=enxik&amp;axn=axnyui&amp;ism=ismyui&amp;rein=tu&amp;ziko=ilm" font-name="kardinal" bold="no" italic="no" font-size="9" font-color="#000000" rotation="0" angle="0" x="320.38" y="182.042" base="189.53" width="7.077" height="10.125">tu</TOKEN><TOKEN sid="p234_s22995" id="p234_w38" href="http://mindsc.ape.jp/klel/yui.cgi?xik=enxik&amp;axn=axnyui&amp;ism=ismyui&amp;rein=te&amp;ziko=ilm" font-name="kardinal" bold="no" italic="no" font-size="9" font-color="#000000" rotation="0" angle="0" x="331.06" y="182.042" base="189.53" width="7.197" height="10.125">te</TOKEN><TOKEN sid="p234_s22996" id="p234_w39" href="http://mindsc.ape.jp/klel/yui.cgi?xik=enxik&amp;axn=axnyui&amp;ism=ismyui&amp;rein=rig&amp;ziko=ilm" font-name="kardinal" bold="no" italic="no" font-size="9" font-color="#000000" rotation="0" angle="0" x="341.86" y="182.042" base="189.53" width="22.365" height="10.125">rig?"</TOKEN></TEXT><TEXT width="147.194" height="10.125" id="p234_t11" x="48.264" y="199.082"><TOKEN sid="p234_s22998" id="p234_w40" href="http://mindsc.ape.jp/klel/yui.cgi?xik=enxik&amp;axn=axnyui&amp;ism=ismyui&amp;rein=an&amp;ziko=ilm" font-name="kardinal" bold="no" italic="no" font-size="9" font-color="#000000" rotation="0" angle="0" x="48.264" y="199.082" base="206.57" width="10.317" height="10.125">"an</TOKEN><TOKEN sid="p234_s22999" id="p234_w41" href="http://mindsc.ape.jp/klel/yui.cgi?xik=enxik&amp;axn=axnyui&amp;ism=ismyui&amp;rein=lo&amp;ziko=ilm" font-name="kardinal" bold="no" italic="no" font-size="9" font-color="#000000" rotation="0" angle="0" x="62.184" y="199.082" base="206.57" width="6.648" height="10.125">lo</TOKEN><TOKEN sid="p234_s23000" id="p234_w42" href="http://mindsc.ape.jp/klel/yui.cgi?xik=enxik&amp;axn=axnyui&amp;ism=ismyui&amp;rein=ti&amp;ziko=ilm" font-name="kardinal" bold="no" italic="no" font-size="9" font-color="#000000" rotation="0" angle="0" x="72.384" y="199.082" base="206.57" width="7.008" height="10.125">ti</TOKEN><TOKEN sid="p234_s23001" id="p234_w43" href="http://mindsc.ape.jp/klel/yui.cgi?xik=enxik&amp;axn=axnyui&amp;ism=ismyui&amp;rein=asm&amp;ziko=ilm" font-name="kardinal" bold="no" italic="no" font-size="9" font-color="#000000" rotation="0" angle="0" x="83.064" y="199.082" base="206.57" width="8.631" height="10.125">asm</TOKEN><TOKEN sid="p234_s23002" id="p234_w44" href="http://mindsc.ape.jp/klel/yui.cgi?xik=enxik&amp;axn=axnyui&amp;ism=ismyui&amp;rein=fonl&amp;ziko=ilm" font-name="kardinal" bold="no" italic="no" font-size="9" font-color="#000000" rotation="0" angle="0" x="95.304" y="199.082" base="206.57" width="16.218" height="10.125">fonl</TOKEN><TOKEN sid="p234_s23003" id="p234_w45" href="http://mindsc.ape.jp/klel/yui.cgi?xik=enxik&amp;axn=axnyui&amp;ism=ismyui&amp;rein=tuube&amp;ziko=ilm" font-name="kardinal" bold="no" italic="no" font-size="9" font-color="#000000" rotation="0" angle="0" x="115.1" y="199.082" base="206.57" width="22.953" height="10.125">tuube,</TOKEN><TOKEN sid="p234_s23004" id="p234_w46" href="http://mindsc.ape.jp/klel/yui.cgi?xik=enxik&amp;axn=axnyui&amp;ism=ismyui&amp;rein=lein&amp;ziko=ilm" font-name="kardinal" bold="no" italic="no" font-size="9" font-color="#000000" rotation="0" angle="0" x="141.77" y="199.082" base="206.57" width="17.643" height="10.125">lein.</TOKEN><TOKEN sid="p234_s23005" id="p234_w47" href="http://mindsc.ape.jp/klel/yui.cgi?xik=enxik&amp;axn=axnyui&amp;ism=ismyui&amp;rein=ya&amp;ziko=ilm" font-name="kardinal" bold="no" italic="no" font-size="9" font-color="#000000" rotation="0" angle="0" x="163.01" y="199.082" base="206.57" width="8.403" height="10.125">ya,</TOKEN><TOKEN sid="p234_s23006" id="p234_w48" href="http://mindsc.ape.jp/klel/yui.cgi?xik=enxik&amp;axn=axnyui&amp;ism=ismyui&amp;rein=ketta&amp;ziko=ilm" font-name="kardinal" bold="no" italic="no" font-size="9" font-color="#000000" rotation="0" angle="0" x="175.01" y="199.082" base="206.57" width="20.448" height="10.125">ketta!"</TOKEN></TEXT><TEXT width="204.606" height="9" id="p234_t12" x="56.424" y="233.09"><TOKEN sid="p234_s23010" id="p234_w49" font-name="ipa¾©" bold="no" italic="no" font-size="9" font-color="#000000" rotation="0" angle="0" x="56.424" y="233.09" base="241.01" width="204.606" height="9">私たちは自転車に跨ると、文字通り逃げ去っていった。</TOKEN></TEXT><TEXT width="316.021" height="9" id="p234_t13" x="56.424" y="250.13"><TOKEN sid="p234_s23013" id="p234_w50" font-name="ipa¾©" bold="no" italic="no" font-size="9" font-color="#000000" rotation="0" angle="0" x="56.424" y="250.13" base="258.05" width="316.021" height="9">ゕルオゕの街中を抜けると急に田舎になった。ただ郊外に住む人もいるので、かろうじ</TOKEN></TEXT><TEXT width="106.803" height="9" id="p234_t14" x="48.264" y="267.05"><TOKEN sid="p234_s23014" id="p234_w51" font-name="ipa¾©" bold="no" italic="no" font-size="9" font-color="#000000" rotation="0" angle="0" x="48.264" y="267.05" base="274.97" width="106.803" height="9">てまだ道が舗装されている。</TOKEN></TEXT><TEXT width="315.966" height="9" id="p234_t15" x="56.424" y="284.11"><TOKEN sid="p234_s23017" id="p234_w52" font-name="ipa¾©" bold="no" italic="no" font-size="9" font-color="#000000" rotation="0" angle="0" x="56.424" y="284.11" base="292.03" width="315.966" height="9">ゕルオゕは森と泉の地方だ。歴史的に有名な場所で、錬金術や魔法が栄えたところでも</TOKEN></TEXT><TEXT width="25.32" height="9" id="p234_t16" x="48.264" y="301.15"><TOKEN sid="p234_s23018" id="p234_w53" font-name="ipa¾©" bold="no" italic="no" font-size="9" font-color="#000000" rotation="0" angle="0" x="48.264" y="301.15" base="309.07" width="25.32" height="9">ある。</TOKEN></TEXT><TEXT width="316.092" height="9" id="p234_t17" x="56.424" y="318.07"><TOKEN sid="p234_s23021" id="p234_w54" font-name="ipa¾©" bold="no" italic="no" font-size="9" font-color="#000000" rotation="0" angle="0" x="56.424" y="318.07" base="325.99" width="316.092" height="9">流石に今では森は切り開かれ、道ができている。自転車がパンアせずに通れる道だ。レ</TOKEN></TEXT><TEXT width="196.446" height="9" id="p234_t18" x="48.264" y="335.11"><TOKEN sid="p234_s23022" id="p234_w55" font-name="ipa¾©" bold="no" italic="no" font-size="9" font-color="#000000" rotation="0" angle="0" x="48.264" y="335.11" base="343.03" width="196.446" height="9">゗ンの案内に従ってひたすら休みなく自転車を漕ぐ。</TOKEN></TEXT><TEXT width="316.092" height="9" id="p234_t19" x="56.424" y="352.15"><TOKEN sid="p234_s23025" id="p234_w56" font-name="ipa¾©" bold="no" italic="no" font-size="9" font-color="#000000" rotation="0" angle="0" x="56.424" y="352.15" base="360.07" width="316.092" height="9">レ゗ンの体力を見ながらペーガを変えつつ進んでいった。生きるということは大変なこ</TOKEN></TEXT><TEXT width="90.6" height="9" id="p234_t20" x="48.264" y="369.07"><TOKEN sid="p234_s23026" id="p234_w57" font-name="ipa¾©" bold="no" italic="no" font-size="9" font-color="#000000" rotation="0" angle="0" x="48.264" y="369.07" base="376.99" width="90.6" height="9">とだと改めて実感した。</TOKEN></TEXT><TEXT width="302.292" height="9" id="p234_t21" x="56.424" y="386.11"><TOKEN sid="p234_s23029" id="p234_w58" font-name="ipa¾©" bold="no" italic="no" font-size="9" font-color="#000000" rotation="0" angle="0" x="56.424" y="386.11" base="394.03" width="302.292" height="9">林道に入ると日が暮れてきた。街灯がないので夜になったら終わりだ。急がねば。</TOKEN></TEXT><TEXT width="286.006" height="9" id="p234_t22" x="56.424" y="403.18"><TOKEN sid="p234_s23032" id="p234_w59" font-name="ipa¾©" bold="no" italic="no" font-size="9" font-color="#000000" rotation="0" angle="0" x="56.424" y="403.18" base="411.1" width="286.006" height="9">昼に雨が降っていたのだろうか、舗装の途切れた地面はいまだに湿っていた。</TOKEN></TEXT><TEXT width="316.044" height="9" id="p234_t23" x="56.424" y="420.1"><TOKEN sid="p234_s23035" id="p234_w60" font-name="ipa¾©" bold="no" italic="no" font-size="9" font-color="#000000" rotation="0" angle="0" x="56.424" y="420.1" base="428.02" width="316.044" height="9">まずい、これ以上無理に進めば転倒して怪我をするかもしれない。そうしたらかえって</TOKEN></TEXT><TEXT width="237.129" height="9" id="p234_t24" x="48.264" y="437.14"><TOKEN sid="p234_s23036" id="p234_w61" font-name="ipa¾©" bold="no" italic="no" font-size="9" font-color="#000000" rotation="0" angle="0" x="48.264" y="437.14" base="445.06" width="237.129" height="9">時間がかかる。かといってこんな林の中で野宿などできようか。</TOKEN></TEXT><TEXT width="314.588" height="9.873" id="p234_t25" x="56.424" y="454.18"><TOKEN sid="p234_s23039" id="p234_w62" font-name="ipa¾©" bold="no" italic="no" font-size="9" font-color="#000000" rotation="0" angle="0" x="56.424" y="454.18" base="462.1" width="49.8" height="9">隠れ家はもう</TOKEN><TOKEN sid="p234_s23040" id="p234_w63" font-name="times new roman" symbolic="yes" serif="yes" fixed-width="yes" bold="no" italic="no" font-size="9" font-color="#000000" rotation="0" angle="0" x="107.42" y="455.953" base="462.1" width="8.58" height="8.1">10</TOKEN><TOKEN sid="p234_s23041" id="p234_w64" font-name="ipa¾©" bold="no" italic="no" font-size="9" font-color="#000000" rotation="0" angle="0" x="117.5" y="454.18" base="462.1" width="253.512" height="9">分ほどだと言う。ついに日が暮れたので、自転車から降りて歩くこと</TOKEN></TEXT><TEXT width="33.48" height="9" id="p234_t26" x="48.264" y="471.1"><TOKEN sid="p234_s23042" id="p234_w65" font-name="ipa¾©" bold="no" italic="no" font-size="9" font-color="#000000" rotation="0" angle="0" x="48.264" y="471.1" base="479.02" width="33.48" height="9">にした。</TOKEN></TEXT><TEXT width="315.966" height="9" id="p234_t27" x="56.424" y="488.136"><TOKEN sid="p234_s23045" id="p234_w66" font-name="ipa¾©" bold="no" italic="no" font-size="9" font-color="#000000" rotation="0" angle="0" x="56.424" y="488.136" base="496.056" width="315.966" height="9">ゞラゞラと車輪の音が響く。木々のざわめきが不気味に聞こえる。道なりに進んでいる</TOKEN></TEXT><TEXT width="328.218" height="9" id="p234_t28" x="48.264" y="505.2"><TOKEN sid="p234_s23046" id="p234_w67" font-name="ipa¾©" bold="no" italic="no" font-size="9" font-color="#000000" rotation="0" angle="0" x="48.264" y="505.2" base="513.12" width="147.486" height="9">ので辛うじて迷わないですんでいるが、</TOKEN><TOKEN sid="p234_s23047" id="p234_w68" font-name="ipa¾©" bold="no" italic="no" font-size="9" font-color="#000000" rotation="0" angle="0" x="191.553" y="505.2" base="513.12" width="90.6" height="9">ここで迷えば終わりだ。</TOKEN><TOKEN sid="p234_s23048" id="p234_w69" font-name="ipa¾©" bold="no" italic="no" font-size="9" font-color="#000000" rotation="0" angle="0" x="277.956" y="505.2" base="513.12" width="98.526" height="9">なにせゕンギが使えない。</TOKEN></TEXT><TEXT width="188.286" height="9" id="p234_t29" x="56.424" y="539.16"><TOKEN sid="p234_s23052" id="p234_w70" font-name="ipa¾©" bold="no" italic="no" font-size="9" font-color="#000000" rotation="0" angle="0" x="56.424" y="539.16" base="547.08" width="188.286" height="9">降りてしばらく歩くと、ようやく隠れ家に着いた。</TOKEN></TEXT></PAGE>
