<?xml version="1.0" encoding="UTF-8"?>
<PAGE width="419.64" height="595.32" number="192" id="p192"><MEDIABOX x1="0" y1="0" x2="419.64" y2="595.32"/><CROPBOX x1="0" y1="0" x2="419.64" y2="595.32"/><BLEEDBOX x1="0" y1="0" x2="419.64" y2="595.32"/><ARTBOX x1="0" y1="0" x2="419.64" y2="595.32"/><TRIMBOX x1="0" y1="0" x2="419.64" y2="595.32"/><TEXT width="12.7715" height="7.668" id="p192_t1" x="203.45" y="569.101"><TOKEN sid="p192_s19104" id="p192_w1" font-name="Times New Roman" symbolic="yes" serif="yes" fixed-width="yes" bold="no" italic="no" font-size="8.52" font-color="#000000" rotation="0" angle="0" x="203.45" y="569.101" base="574.92" width="12.7715" height="7.668">192</TOKEN></TEXT><TEXT width="316.166" height="9" id="p192_t2" x="56.424" y="46.08"><TOKEN sid="p192_s19107" id="p192_w2" font-name="IPA¾©" bold="no" italic="no" font-size="9" font-color="#000000" rotation="0" angle="0" x="56.424" y="46.08" base="54" width="237.182" height="9">どうやらレプリゞではなく本物の神の武器だと言いたいようだ。</TOKEN><TOKEN sid="p192_s19108" id="p192_w3" font-name="ipa¾©" bold="no" italic="no" font-size="9" font-color="#000000" rotation="0" angle="0" x="290.123" y="46.08" base="54" width="82.467" height="9">そしてそれを持ってい</TOKEN></TEXT><TEXT width="269.652" height="9" id="p192_t3" x="48.264" y="63.02"><TOKEN sid="p192_s19109" id="p192_w4" font-name="ipa¾©" bold="no" italic="no" font-size="9" font-color="#000000" rotation="0" angle="0" x="48.264" y="63.02" base="70.94" width="269.652" height="9">ることをある人から隠すためにお父さんは事故死を演じてみせたと言う。</TOKEN></TEXT><TEXT width="316.161" height="9" id="p192_t4" x="56.424" y="80.06"><TOKEN sid="p192_s19112" id="p192_w5" font-name="ipa¾©" bold="no" italic="no" font-size="9" font-color="#000000" rotation="0" angle="0" x="56.424" y="80.06" base="87.98" width="316.161" height="9">本来なら「寝言は寝て言え」と張り倒すところだが、神がなくしたヴゔガトリゕを召喚</TOKEN></TEXT><TEXT width="324.252" height="9" id="p192_t5" x="48.264" y="97.1"><TOKEN sid="p192_s19113" id="p192_w6" font-name="ipa¾©" bold="no" italic="no" font-size="9" font-color="#000000" rotation="0" angle="0" x="48.264" y="97.1" base="105.02" width="324.252" height="9">省が躍起になって探しているという事前情報があったため、私たちはもしやと思って彼の</TOKEN></TEXT><TEXT width="82.44" height="9" id="p192_t6" x="48.264" y="114.02"><TOKEN sid="p192_s19114" id="p192_w7" font-name="ipa¾©" bold="no" italic="no" font-size="9" font-color="#000000" rotation="0" angle="0" x="48.264" y="114.02" base="121.94" width="82.44" height="9">話を聞くことにした。</TOKEN></TEXT><TEXT width="84.167" height="10.125" id="p192_t7" x="48.264" y="148.052"><TOKEN sid="p192_s19117" id="p192_w8" href="http://mindsc.ape.jp/klel/yui.cgi?xik=enxik&amp;axn=axnyui&amp;ism=ismyui&amp;rein=xion&amp;ziko=ilm" font-name="kardinal" fixed-width="yes" bold="no" italic="no" font-size="9" font-color="#000000" rotation="0" angle="0" x="48.264" y="148.052" base="155.54" width="22.083" height="10.125">"xion,</TOKEN><TOKEN sid="p192_s19118" id="p192_w9" href="http://mindsc.ape.jp/klel/yui.cgi?xik=enxik&amp;axn=axnyui&amp;ism=ismyui&amp;rein=an&amp;ziko=ilm" font-name="kardinal" fixed-width="yes" bold="no" italic="no" font-size="9" font-color="#000000" rotation="0" angle="0" x="74.064" y="148.052" base="155.54" width="6.717" height="10.125">an</TOKEN><TOKEN sid="p192_s19119" id="p192_w10" href="http://mindsc.ape.jp/klel/yui.cgi?xik=enxik&amp;axn=axnyui&amp;ism=ismyui&amp;rein=ret&amp;ziko=ilm" font-name="kardinal" fixed-width="yes" bold="no" italic="no" font-size="9" font-color="#000000" rotation="0" angle="0" x="84.384" y="148.052" base="155.54" width="11.853" height="10.125">ret</TOKEN><TOKEN sid="p192_s19120" id="p192_w11" href="http://mindsc.ape.jp/klel/yui.cgi?xik=enxik&amp;axn=axnyui&amp;ism=ismyui&amp;rein=xe&amp;ziko=ilm" font-name="kardinal" fixed-width="yes" bold="no" italic="no" font-size="9" font-color="#000000" rotation="0" angle="0" x="99.984" y="148.052" base="155.54" width="7.797" height="10.125">xe</TOKEN><TOKEN sid="p192_s19121" id="p192_w12" href="http://mindsc.ape.jp/klel/yui.cgi?xik=enxik&amp;axn=axnyui&amp;ism=ismyui&amp;rein=a&amp;ziko=ilm" font-name="kardinal" fixed-width="yes" bold="no" italic="no" font-size="9" font-color="#000000" rotation="0" angle="0" x="111.5" y="148.052" base="155.54" width="2.061" height="10.125">a</TOKEN><TOKEN sid="p192_s19122" id="p192_w13" href="http://mindsc.ape.jp/klel/yui.cgi?xik=enxik&amp;axn=axnyui&amp;ism=ismyui&amp;rein=ti&amp;ziko=ilm" font-name="kardinal" fixed-width="yes" bold="no" italic="no" font-size="9" font-color="#000000" rotation="0" angle="0" x="117.14" y="148.052" base="155.54" width="15.291" height="10.125">ti..."</TOKEN></TEXT><TEXT width="316.092" height="9" id="p192_t8" x="56.424" y="165.05"><TOKEN sid="p192_s19125" id="p192_w14" font-name="ipa¾©" bold="no" italic="no" font-size="9" font-color="#000000" rotation="0" angle="0" x="56.424" y="165.05" base="172.97" width="316.092" height="9">話が深刻だと判断したのだろう、ゕルオ゚さんは私にドゕのところでネブラが逃げない</TOKEN></TEXT><TEXT width="188.286" height="9" id="p192_t9" x="48.264" y="182.09"><TOKEN sid="p192_s19126" id="p192_w15" font-name="ipa¾©" bold="no" italic="no" font-size="9" font-color="#000000" rotation="0" angle="0" x="48.264" y="182.09" base="190.01" width="188.286" height="9">よう念のため見張っていてくれと耳打ちしてきた。</TOKEN></TEXT><TEXT width="315.966" height="9" id="p192_t10" x="56.424" y="199.13"><TOKEN sid="p192_s19129" id="p192_w16" font-name="ipa¾©" bold="no" italic="no" font-size="9" font-color="#000000" rotation="0" angle="0" x="56.424" y="199.13" base="207.05" width="315.966" height="9">言われるままドゕの前に立つ。流石にここからでは会話が聞き取れないが、様子は伺え</TOKEN></TEXT><TEXT width="17.16" height="9" id="p192_t11" x="48.264" y="216.05"><TOKEN sid="p192_s19130" id="p192_w17" font-name="ipa¾©" bold="no" italic="no" font-size="9" font-color="#000000" rotation="0" angle="0" x="48.264" y="216.05" base="223.97" width="17.16" height="9">る。</TOKEN></TEXT><TEXT width="319.809" height="9" id="p192_t12" x="56.424" y="233.09"><TOKEN sid="p192_s19133" id="p192_w18" font-name="ipa¾©" bold="no" italic="no" font-size="9" font-color="#000000" rotation="0" angle="0" x="56.424" y="233.09" base="241.01" width="319.809" height="9">ネブラの話が進むにつれ、レ゗ンは前のめりになっていった。目には涙を貯めている。</TOKEN></TEXT><TEXT width="188.327" height="9" id="p192_t13" x="48.264" y="250.13"><TOKEN sid="p192_s19134" id="p192_w19" font-name="ipa¾©" bold="no" italic="no" font-size="9" font-color="#000000" rotation="0" angle="0" x="48.264" y="250.13" base="258.05" width="188.327" height="9">一方ゕルオ゚さんはゴラゴラと杖を気にしている。</TOKEN></TEXT><TEXT width="24.768" height="10.125" id="p192_t14" x="48.264" y="267.002"><TOKEN sid="p192_s19136" id="p192_w20" href="http://mindsc.ape.jp/klel/yui.cgi?xik=enxik&amp;axn=axnyui&amp;ism=ismyui&amp;rein=arte&amp;ziko=ilm" font-name="kardinal" fixed-width="yes" bold="no" italic="no" font-size="9" font-color="#000000" rotation="0" angle="0" x="48.264" y="267.002" base="274.49" width="24.768" height="10.125">"arte!"</TOKEN></TEXT><TEXT width="302.292" height="9" id="p192_t15" x="56.424" y="284.11"><TOKEN sid="p192_s19139" id="p192_w21" font-name="ipa¾©" bold="no" italic="no" font-size="9" font-color="#000000" rotation="0" angle="0" x="56.424" y="284.11" base="292.03" width="302.292" height="9">あるとき一段と大きいレ゗ンの声が聞こえた。見ると二人とも青い顔をしている。</TOKEN></TEXT><TEXT width="316.092" height="9" id="p192_t16" x="56.424" y="301.15"><TOKEN sid="p192_s19142" id="p192_w22" font-name="ipa¾©" bold="no" italic="no" font-size="9" font-color="#000000" rotation="0" angle="0" x="56.424" y="301.15" base="309.07" width="316.092" height="9">それからしばらくしてゕルオ゚さんは警察を呼んだ。ネブラから事情聴取を終えたので</TOKEN></TEXT><TEXT width="324.269" height="9.873" id="p192_t17" x="48.264" y="318.07"><TOKEN sid="p192_s19143" id="p192_w23" font-name="ipa¾©" bold="no" italic="no" font-size="9" font-color="#000000" rotation="0" angle="0" x="48.264" y="318.07" base="325.99" width="161.286" height="9">引き渡すことにしたようだ。いくら同僚でも</TOKEN><TOKEN sid="p192_s19144" id="p192_w24" font-name="times new roman" symbolic="yes" serif="yes" fixed-width="yes" bold="no" italic="no" font-size="9" font-color="#000000" rotation="0" angle="0" x="210.77" y="319.843" base="325.99" width="4.5" height="8.1">2</TOKEN><TOKEN sid="p192_s19145" id="p192_w25" font-name="ipa¾©" bold="no" italic="no" font-size="9" font-color="#000000" rotation="0" angle="0" x="216.77" y="318.07" base="325.99" width="155.763" height="9">度もナ゗フで襲ってきたのだから致し方が</TOKEN></TEXT><TEXT width="49.8" height="9" id="p192_t18" x="48.264" y="335.11"><TOKEN sid="p192_s19146" id="p192_w26" font-name="ipa¾©" bold="no" italic="no" font-size="9" font-color="#000000" rotation="0" angle="0" x="48.264" y="335.11" base="343.03" width="49.8" height="9">ないだろう。</TOKEN></TEXT><TEXT width="316.046" height="9" id="p192_t19" x="56.424" y="369.07"><TOKEN sid="p192_s19150" id="p192_w27" font-name="ipa¾©" bold="no" italic="no" font-size="9" font-color="#000000" rotation="0" angle="0" x="56.424" y="369.07" base="376.99" width="316.046" height="9">警察にネブラを任せた後、私はゕルオ゚さんから説明を受けた。レ゗ンは何やらオョッ</TOKEN></TEXT><TEXT width="180.126" height="9" id="p192_t20" x="48.264" y="386.11"><TOKEN sid="p192_s19151" id="p192_w28" font-name="ipa¾©" bold="no" italic="no" font-size="9" font-color="#000000" rotation="0" angle="0" x="48.264" y="386.11" base="394.03" width="180.126" height="9">アが大きかったそうで、喋る気力がないらしい。</TOKEN></TEXT><TEXT width="123.006" height="9" id="p192_t21" x="56.424" y="403.18"><TOKEN sid="p192_s19154" id="p192_w29" font-name="ipa¾©" bold="no" italic="no" font-size="9" font-color="#000000" rotation="0" angle="0" x="56.424" y="403.18" base="411.1" width="123.006" height="9">話の内容は驚くべきものだった。</TOKEN></TEXT><TEXT width="316.043" height="9.873" id="p192_t22" x="56.424" y="420.1"><TOKEN sid="p192_s19157" id="p192_w30" font-name="ipa¾©" bold="no" italic="no" font-size="9" font-color="#000000" rotation="0" angle="0" x="56.424" y="420.1" base="428.02" width="82.44" height="9">ト゘ッテゖがなくした</TOKEN><TOKEN sid="p192_s19158" id="p192_w31" font-name="times new roman" symbolic="yes" serif="yes" fixed-width="yes" bold="no" italic="no" font-size="9" font-color="#000000" rotation="0" angle="0" x="140.09" y="421.873" base="428.02" width="4.5" height="8.1">2</TOKEN><TOKEN sid="p192_s19159" id="p192_w32" font-name="ipa¾©" bold="no" italic="no" font-size="9" font-color="#000000" rotation="0" angle="0" x="146.09" y="420.1" base="428.02" width="220.86" height="9">つのヴゔガトリゕのうちのひとつはヴゔルデだったらしい。</TOKEN><TOKEN sid="p192_s19160" id="p192_w33" font-name="ipa¾©" bold="no" italic="no" font-size="9" font-color="#000000" rotation="0" angle="0" x="363.467" y="420.1" base="428.02" width="9" height="9">こ</TOKEN></TEXT><TEXT width="324.252" height="9" id="p192_t23" x="48.264" y="437.14"><TOKEN sid="p192_s19161" id="p192_w34" font-name="ipa¾©" bold="no" italic="no" font-size="9" font-color="#000000" rotation="0" angle="0" x="48.264" y="437.14" base="445.06" width="324.252" height="9">のことはゕルオ゚さんも知らなかった。ハ゗ンさんらしか知らない事実をネブラは調べ上</TOKEN></TEXT><TEXT width="41.64" height="9" id="p192_t24" x="48.264" y="454.18"><TOKEN sid="p192_s19162" id="p192_w35" font-name="ipa¾©" bold="no" italic="no" font-size="9" font-color="#000000" rotation="0" angle="0" x="48.264" y="454.18" base="462.1" width="41.64" height="9">げていた。</TOKEN></TEXT><TEXT width="315.966" height="9" id="p192_t25" x="56.424" y="471.1"><TOKEN sid="p192_s19165" id="p192_w36" font-name="ipa¾©" bold="no" italic="no" font-size="9" font-color="#000000" rotation="0" angle="0" x="56.424" y="471.1" base="479.02" width="315.966" height="9">ネブラはこの家に置いてある杖が本物のヴゔルデだという。しかし釈然としない。ヴゔ</TOKEN></TEXT><TEXT width="324.252" height="9" id="p192_t26" x="48.264" y="488.136"><TOKEN sid="p192_s19166" id="p192_w37" font-name="ipa¾©" bold="no" italic="no" font-size="9" font-color="#000000" rotation="0" angle="0" x="48.264" y="488.136" base="496.056" width="324.252" height="9">ガトリゕの件は召喚省でも一握りの人間しか知らないはず。魔法研究所所属のド゘ルゟさ</TOKEN></TEXT><TEXT width="90.6" height="9" id="p192_t27" x="48.264" y="505.2"><TOKEN sid="p192_s19167" id="p192_w38" font-name="ipa¾©" bold="no" italic="no" font-size="9" font-color="#000000" rotation="0" angle="0" x="48.264" y="505.2" base="513.12" width="90.6" height="9">んとは何ら関係がない。</TOKEN></TEXT><TEXT width="316.158" height="9" id="p192_t28" x="56.424" y="522.12"><TOKEN sid="p192_s19171" id="p192_w39" font-name="ipa¾©" bold="no" italic="no" font-size="9" font-color="#000000" rotation="0" angle="0" x="56.424" y="522.12" base="530.04" width="237.174" height="9">ところが意外なところでド゘ルゟさんに繋がることが分かった。</TOKEN><TOKEN sid="p192_s19172" id="p192_w40" font-name="ipa¾©" bold="no" italic="no" font-size="9" font-color="#000000" rotation="0" angle="0" x="290.115" y="522.12" base="530.04" width="82.467" height="9">魔法研究所は召喚省の</TOKEN></TEXT><TEXT width="324.126" height="9" id="p192_t29" x="48.264" y="539.16"><TOKEN sid="p192_s19173" id="p192_w41" font-name="ipa¾©" bold="no" italic="no" font-size="9" font-color="#000000" rotation="0" angle="0" x="48.264" y="539.16" base="547.08" width="324.126" height="9">下位機関なのだが、ときおり召喚省の隠れ蓑として使われることがあるそうだ。つまり実</TOKEN></TEXT></PAGE>
